{
    "teensy41": {
        "name": "Teensy 4.1",
        "dimensions": {
            "width": 18,
            "height": 61,
            "ratio": 0.295,
            "connectorOffset": 20
        },
        "pinLayout": {
            "leftCount": 22,
            "rightCount": 20,
            "topCount": 6,
            "bottomCount": 7
        },
        "capabilities": [
            "digital",
            "analog",
            "pwm",
            "serial",
            "i2c",
            "spi",
            "can",
            "audio"
        ]
    },
    "teensy40": {
        "name": "Teensy 4.0",
        "dimensions": {
            "width": 35.0,
            "height": 17.8,
            "ratio": 1.97
        },
        "pinLayout": {
            "leftCount": 13,
            "rightCount": 11,
            "topCount": 6,
            "bottomCount": 10
        },
        "capabilities": [
            "digital",
            "analog",
            "pwm",
            "serial",
            "i2c",
            "spi",
            "can",
            "audio"
        ]
    }
}